git_mr_linear/__init__.py
git_mr_linear/auth.py
git_mr_linear/cfg.py
git_mr_linear/logger.py
git_mr_linear/main.py
git_mr_linear-0.0.6a0.dist-info/LICENSE
git_mr_linear-0.0.6a0.dist-info/METADATA
git_mr_linear-0.0.6a0.dist-info/WHEEL
git_mr_linear-0.0.6a0.dist-info/entry_points.txt
git_mr_linear-0.0.6a0.dist-info/top_level.txt
git_mr_linear-0.0.6a0.dist-info/RECORD
