Metadata-Version: 2.1
Name: git-mr-linear
Version: 0.0.6a0
Summary: A command line utility to list and merge gitlab merge requests while maintaining linear history
Home-page: https://gitlab.com/dhpersonal/git-mr-linear
Author: Donghyeon Kim
Author-email: dhygns@gmail.com
Classifier: Programming Language :: Python :: 3
Classifier: License :: OSI Approved :: MIT License
Classifier: Operating System :: OS Independent
Classifier: Development Status :: 2 - Pre-Alpha
Classifier: Intended Audience :: Developers
Classifier: Topic :: Software Development :: Version Control :: Git
Requires-Python: >=3.6
License-File: LICENSE
